[
  {
    "id": 0,
    "samples": [
      {
        "id": 0,
        "title": "Loading..."
      },
      {
        "id": 1,
        "title": "Toast"
      },
      {
        "id": 2,
        "title": "Dialog"
      },
      {
        "id": 3,
        "title": "Alert"
      },
      {
        "id": 4,
        "title": "Input"
      },
      {
        "id": 5,
        "title": "Log"
      }
    ]
  },
  {
    "id": 1,
    "samples": [
      {
        "id": 0,
        "title": "Button"
      }
    ]
  },
  {
    "id": 2,
    "samples": [
      {
        "id": 0,
        "title": "首页嵌套"
      }
    ]
  }
]